[[{"location":"G:\\Code\\JavaEEProject\\repository\\org\\freemarker\\freemarker\\2.3.23\\freemarker-2.3.23.jar","type":"JAR","hints":{}},"org.freemarker.freemarker:org.freemarker.freemarker:2.3.23"],[{"location":"G:\\Code\\JavaEEProject\\e3-item-web","type":"PROJECT","hints":{"PROJECT_NAME":"e3-item-web"}},"cn.e3mall:e3-item-web:0.0.1"],[{"location":"G:\\Code\\JavaEEProject\\repository\\org\\apache\\activemq\\activemq-all\\5.11.2\\activemq-all-5.11.2.jar","type":"JAR","hints":{}},"ABSENT"],[{"location":"G:\\Code\\JavaEEProject\\e3-manager\\e3-manager-interface","type":"PROJECT","hints":{"PROJECT_NAME":"e3-manager-interface"}},"cn.e3mall:e3-manager-interface:0.0.1"],[{"location":"G:\\Code\\JavaEEProject\\repository\\org\\springframework\\spring-webmvc\\4.2.4.RELEASE\\spring-webmvc-4.2.4.RELEASE.jar","type":"JAR","hints":{}},"ABSENT"],[{"location":"G:\\DevelopTools\\Java\\jdk1.8.0_152","type":"JRE","hints":{"EXECUTION_ENVIRONMENT":"JavaSE-1.8"}},"jre:jre:1.8.0"]]